<?xml version="1.0" encoding="utf-8"?>
<!-- Copyright (C) 2013-Today  Carlos Eduardo Vercelino - CLVsol
     License AGPL-3.0 or later (http://www.gnu.org/licenses/agpl). -->

<odoo>

    <record id="clv_patient_mass_edit_view_form" model="ir.ui.view">
        <field name="name">clv.patient.mass_edit.form</field>
        <field name="model">clv.patient.mass_edit</field>
        <field name="arch" type="xml">
            <form>
                <div class="oe_right">
                </div>
                <label for="patient_ids"/>
                <field name="patient_ids"/>
                <group>
                    <group name="reg_state_selection">
                        <field name="reg_state_selection"/>
                    </group>
                    <group>
                        <field name="reg_state" nolabel='1'/>
                    </group>
                    <group>
                        <field name="state_selection"/>
                    </group>
                    <group>
                        <field name="state" nolabel='1'/>
                    </group>
                    <group name="global_tag_ids_selection">
                        <field name="global_tag_ids_selection"/>
                    </group>
                    <group>
                        <field name="global_tag_ids" options="{'no_open': False, 'no_create': True}" nolabel='1'/>
                    </group>
                    <group>
                        <field name="tag_ids_selection"/>
                    </group>
                    <group name="tag_ids">
                        <field name="tag_ids" options="{'no_open': False, 'no_create': True}" nolabel='1'/>
                    </group>
                    <group>
                        <field name="category_ids_selection"/>
                    </group>
                    <group>
                        <field name="category_ids" options="{'no_open': False, 'no_create': True}" nolabel='1'/>
                    </group>
                    <group>
                        <field name="marker_ids_selection"/>
                    </group>
                    <group name="marker_ids">
                        <field name="marker_ids" options="{'no_open': False, 'no_create': True}" nolabel='1'/>
                    </group>
                    <group>
                        <field name="employee_id_selection"/>
                    </group>
                    <group name="employee_id">
                        <field name="employee_id" options="{'no_open': False, 'no_create': True}" nolabel='1'/>
                    </group>
                    <group>
                        <field name="get_employee_id"/>
                    </group>
                    <group name="get_employee_id">
                    </group>
                    <group>
                        <field name="random_field_selection"/>
                    </group>
                    <group name="random_field">
                        <field name="random_field" nolabel='1'/>
                    </group>
                    <group>
                        <field name="phase_id_selection"/>
                    </group>
                    <group name="phase_id">
                        <field name="phase_id" options="{'no_open': False, 'no_create': True}" nolabel='1'/>
                    </group>
                    <group name="partner_entity_code_selection">
                        <field name="partner_entity_code_selection"/>
                    </group>
                    <group>
                    </group>
                    <group>
                        <field name="patient_ref_age_refresh"/>
                    </group>
                    <group name="patient_ref_age_refresh">
                    </group>
                    <group>
                        <field name="active_log_selection"/>
                    </group>
                    <group name="active_log">
                        <field name="active_log" nolabel='1'/>
                    </group>
                </group>
                <footer>
                    <button 
                        type="object"
                        name="do_patient_mass_edit"
                        string="Mass Edit"
                        class="oe_highlight"
                        />
                    <button special="cancel" string="Cancel"/>
                </footer>
            </form>

        </field>
    </record>

    <!-- More button Action -->
    <record id="clv_patient_mass_edit_action" model="ir.actions.act_window">
        <field name="name">Patient Mass Edit</field>
        <field name="binding_model_id" ref="model_clv_patient"/>
        <field name="res_model">clv.patient.mass_edit</field>
        <field name="view_mode">form</field>
        <field name="target">new</field>
    </record>

</odoo>
